leakz/__init__.py
leakz/api.py
leakz/exceptions.py
leakz-1.3.2.dist-info/METADATA
leakz-1.3.2.dist-info/RECORD
leakz-1.3.2.dist-info/WHEEL
leakz-1.3.2.dist-info/top_level.txt
